assets_tags/__init__.py
assets_tags/admin.py
assets_tags/apps.py
assets_tags/models.py
assets_tags/tests.py
assets_tags/views.py
assets_tags/migrations/__init__.py
assets_tags/templatetags/__init__.py
assets_tags/templatetags/asset_tags.py
example_project/__init__.py
example_project/asgi.py
example_project/settings.py
example_project/urls.py
example_project/wsgi.py
django_assets_tags-0.1.dist-info/LICENSE
django_assets_tags-0.1.dist-info/METADATA
django_assets_tags-0.1.dist-info/WHEEL
django_assets_tags-0.1.dist-info/top_level.txt
django_assets_tags-0.1.dist-info/RECORD
